pep8.py
pep8-1.6.1.dist-info/WHEEL
pep8-1.6.1.dist-info/entry_points.txt
pep8-1.6.1.dist-info/metadata.json
pep8-1.6.1.dist-info/DESCRIPTION.rst
pep8-1.6.1.dist-info/namespace_packages.txt
pep8-1.6.1.dist-info/METADATA
pep8-1.6.1.dist-info/top_level.txt
pep8-1.6.1.dist-info/RECORD
