Metadata-Version: 2.0
Name: pep8
Version: 1.6.1
Summary: Python style guide checker
Home-page: http://pep8.readthedocs.org/
Author: Johann C. Rocholl
Author-email: johann@rocholl.net
License: Expat license
Keywords: pep8
Platform: UNKNOWN
Classifier: Development Status :: 5 - Production/Stable
Classifier: Environment :: Console
Classifier: Intended Audience :: Developers
Classifier: License :: OSI Approved :: MIT License
Classifier: Operating System :: OS Independent
Classifier: Programming Language :: Python
Classifier: Programming Language :: Python :: 2
Classifier: Programming Language :: Python :: 3
Classifier: Topic :: Software Development :: Libraries :: Python Modules
